streamlit_utils/__init__.py
streamlit_utils/py.typed
streamlit_utils/state.py
streamlit_utils-0.1.1.dist-info/LICENSE
streamlit_utils-0.1.1.dist-info/METADATA
streamlit_utils-0.1.1.dist-info/WHEEL
streamlit_utils-0.1.1.dist-info/top_level.txt
streamlit_utils-0.1.1.dist-info/RECORD
