Metadata-Version: 2.1
Name: streamlit-utils
Version: 0.1.1
Summary: General utilities to make streamlit app creation easier in an object-oriented manner.
Author-email: Marcelo Soares <marcelo.me.soares@gmail.com>
License: MIT License
Project-URL: Homepage, https://github.com/marcelomendoncasoares/streamlit-utils
Project-URL: Release Notes, https://github.com/marcelomendoncasoares/streamlit-utils/blob/main/CHANGELOG.md
Project-URL: Source Code, https://github.com/marcelomendoncasoares/streamlit-utils
Classifier: Development Status :: 4 - Beta
Classifier: Environment :: Console
Classifier: Environment :: Web Environment
Classifier: Intended Audience :: Developers
Classifier: Intended Audience :: Science/Research
Classifier: License :: OSI Approved :: MIT License
Classifier: Programming Language :: Python :: 3.8
Classifier: Programming Language :: Python :: 3.9
Classifier: Programming Language :: Python :: 3.10
Classifier: Programming Language :: Python :: 3.11
Classifier: Topic :: Scientific/Engineering :: Visualization
Classifier: Topic :: Software Development :: Libraries :: Application Frameworks
Classifier: Topic :: Software Development :: Libraries :: Python Modules
Classifier: Topic :: Software Development :: Widget Sets
Classifier: Typing :: Typed
Requires-Python: >=3.8
License-File: LICENSE
Requires-Dist: streamlit
Provides-Extra: dev
Requires-Dist: pre-commit ; extra == 'dev'
Requires-Dist: pytest ; extra == 'dev'
Requires-Dist: pytest-cov ; extra == 'dev'
